{
  "schemaVersion": 1,
  "id": "fabricenchantments",
  "version": "0.1.0",

  "name": "Fabric Enchantments",
  "description": "An enchantment overhual mod for Fabric",
  "authors": [
    "Safro"
  ],
  "contact": {
    "homepage": "https://fabricmc.net/",
    "sources": "https://github.com/FabricMC/fabric-example-mod"
  },

  "license": "All Rights Reserved",
  "icon": "assets/fabricenchantments/icon.png",

  "environment": "*",
  "entrypoints": {
    "main": [
      "safro.fabric.enchantments.FabricEnchantments"
    ]
  },
  "mixins": [
    "fabricenchantments.mixins.json"
  ],

  "depends": {
    "fabricloader": ">=0.11.3",
    "fabric": "*",
    "minecraft": "1.17.x",
    "java": ">=16"
  },
  "suggests": {
    "another-mod": "*"
  }
}